parallel/__init__.py
parallel/_base_client.py
parallel/_client.py
parallel/_compat.py
parallel/_constants.py
parallel/_exceptions.py
parallel/_files.py
parallel/_models.py
parallel/_qs.py
parallel/_resource.py
parallel/_response.py
parallel/_streaming.py
parallel/_types.py
parallel/_version.py
parallel/py.typed
parallel/_utils/__init__.py
parallel/_utils/_compat.py
parallel/_utils/_datetime_parse.py
parallel/_utils/_logs.py
parallel/_utils/_proxy.py
parallel/_utils/_reflection.py
parallel/_utils/_resources_proxy.py
parallel/_utils/_streams.py
parallel/_utils/_sync.py
parallel/_utils/_transform.py
parallel/_utils/_typing.py
parallel/_utils/_utils.py
parallel/lib/.keep
parallel/lib/__init__.py
parallel/lib/_pydantic.py
parallel/lib/_time.py
parallel/lib/_parsing/__init__.py
parallel/lib/_parsing/_task_run_result.py
parallel/lib/_parsing/_task_spec.py
parallel/resources/__init__.py
parallel/resources/task_run.py
parallel/resources/beta/__init__.py
parallel/resources/beta/beta.py
parallel/resources/beta/findall.py
parallel/resources/beta/task_group.py
parallel/resources/beta/task_run.py
parallel/types/__init__.py
parallel/types/auto_schema.py
parallel/types/auto_schema_param.py
parallel/types/citation.py
parallel/types/field_basis.py
parallel/types/json_schema.py
parallel/types/json_schema_param.py
parallel/types/parsed_task_run_result.py
parallel/types/task_run.py
parallel/types/task_run_create_params.py
parallel/types/task_run_json_output.py
parallel/types/task_run_result.py
parallel/types/task_run_result_params.py
parallel/types/task_run_text_output.py
parallel/types/task_spec.py
parallel/types/task_spec_param.py
parallel/types/text_schema.py
parallel/types/text_schema_param.py
parallel/types/beta/__init__.py
parallel/types/beta/beta_extract_params.py
parallel/types/beta/beta_run_input.py
parallel/types/beta/beta_run_input_param.py
parallel/types/beta/beta_search_params.py
parallel/types/beta/beta_task_run_result.py
parallel/types/beta/error_event.py
parallel_web-0.3.4.dist-info/METADATA
parallel_web-0.3.4.dist-info/WHEEL
parallel_web-0.3.4.dist-info/licenses/LICENSE
parallel_web-0.3.4.dist-info/RECORD
